quantstats/__init__.py
quantstats/plots.py
quantstats/report.html
quantstats/reports.py
quantstats/stats.py
quantstats/utils.py
quantstats/version.py
quantstats/_plotting/__init__.py
quantstats/_plotting/core.py
quantstats/_plotting/wrappers.py
quantstatsqd-0.0.63.dist-info/licenses/LICENSE.txt
quantstatsqd-0.0.63.dist-info/METADATA
quantstatsqd-0.0.63.dist-info/WHEEL
quantstatsqd-0.0.63.dist-info/entry_points.txt
quantstatsqd-0.0.63.dist-info/top_level.txt
quantstatsqd-0.0.63.dist-info/RECORD
